spotify_sdk/__init__.py
spotify_sdk/_async/__init__.py
spotify_sdk/_async/_base_client.py
spotify_sdk/_async/_base_service.py
spotify_sdk/_async/_client.py
spotify_sdk/_async/services/__init__.py
spotify_sdk/_async/services/albums.py
spotify_sdk/_async/services/artists.py
spotify_sdk/_async/services/playlists.py
spotify_sdk/_async/services/tracks.py
spotify_sdk/_sync/__init__.py
spotify_sdk/_sync/_base_client.py
spotify_sdk/_sync/_base_service.py
spotify_sdk/_sync/_client.py
spotify_sdk/_sync/services/__init__.py
spotify_sdk/_sync/services/albums.py
spotify_sdk/_sync/services/artists.py
spotify_sdk/_sync/services/playlists.py
spotify_sdk/_sync/services/tracks.py
spotify_sdk/exceptions.py
spotify_sdk/models/__init__.py
spotify_sdk/models/album.py
spotify_sdk/models/artist.py
spotify_sdk/models/base.py
spotify_sdk/models/common.py
spotify_sdk/models/playlist.py
spotify_sdk/models/track.py
spotify_sdk/py.typed
spotify_sdk-0.3.0.dist-info/WHEEL
spotify_sdk-0.3.0.dist-info/METADATA
spotify_sdk-0.3.0.dist-info/RECORD
